backupz/__init__.py
backupz/__main__.py
backupz/src/__init__.py
backupz/src/features/__init__.py
backupz/src/features/group_make.py
backupz/src/features/impl/__init__.py
backupz/src/features/impl/utils.py
backupz/src/support/__init__.py
backupz/src/support/conf.py
backupz/src/support/dependency.py
backupz/src/support/download.py
backupz/src/support/helper.py
backupz/src/support/output.py
backupz/src/support/progress_alive_bar.py
backupz/src/support/progress_alive_bar_git.py
backupz/src/support/texts.py
backupz/src/support/data/__init__.py
backupz/src/support/data/data_ftp.py
backupz/src/support/data/data_ssh.py
backupz/src/support/data/data_telegram.py
backupz-2.4.0.0.dist-info/LICENSE
backupz-2.4.0.0.dist-info/METADATA
backupz-2.4.0.0.dist-info/WHEEL
backupz-2.4.0.0.dist-info/entry_points.txt
backupz-2.4.0.0.dist-info/top_level.txt
backupz-2.4.0.0.dist-info/RECORD
