Metadata-Version: 2.1
Name: backupz
Version: 2.4.0.0
Summary: The application allows you to generate CHANGELOG files based on Git tags.
Home-page: https://github.com/keygenqt/backupz
Author: Vitaliy Zarubin
Author-email: keygenqt@gmail.com
Requires-Python: >=3.8.2
License-File: LICENSE
Requires-Dist: click >=8.1.7
Requires-Dist: pyYaml >=6.0.1
Requires-Dist: cffi >=1.16.0
Requires-Dist: beautifulsoup4 >=4.12.3
Requires-Dist: alive-progress >=3.1.5
Requires-Dist: paramiko >=3.4.0
Requires-Dist: GitPython >=3.1.41
Requires-Dist: requests >=2.31.0
Requires-Dist: pytube >=15.0.0
Requires-Dist: Telethon >=1.34.0
